tenjin_sdn-0.0.5.dist-info/METADATA
tenjin_sdn-0.0.5.dist-info/WHEEL
tenjin_sdn-0.0.5.dist-info/entry_points.txt
tenjin_sdn-0.0.5.dist-info/licenses/LICENSE
tenjin_sdn/__init__.py
tenjin_sdn/tenjin_sdn.cpython-311-x86_64-linux-gnu.so
tenjin_sdn-0.0.5.dist-info/RECORD
