Metadata-Version: 2.3
Name: tenjin_sdn
Version: 0.0.5
Classifier: Programming Language :: Rust
Classifier: Programming Language :: Python :: Implementation :: CPython
Classifier: Programming Language :: Python :: Implementation :: PyPy
License-File: LICENSE
License-File: LICENSE
Summary: Tenjin is The SDN Framework writing with rust, this library is implement tenjin into python
Keywords: tenjin,openflow,sdn,cli,network
Home-Page: https://github.com/Arikato111/tenjin-py
Author: Nawasan <nawasan.dev@gmail.com>
Author-email: Nawasan Wisitsingkhon <nawasan.dev@gmail.com>
Maintainer-email: Nawasan Wisitsingkhon <nawasan.dev@gmail.com>
License: MIT
Requires-Python: >=3.8
Project-URL: Homepage, https://github.com/Arikato111/tenjin-py
Project-URL: Documentation, https://github.com/Arikato111/Tenjin-py/wiki
Project-URL: Repository, https://github.com/Arikato111/tenjin-py.git
Project-URL: Issues, https://github.com/Arikato111/Tenjin-py/issues
